{
  "jurisdiction": "PH",
  "section_id": "57",
  "title": "Pre-Employment Medical Examination. The licensed manning agency",
  "content": "21 shall ensure that the Pre-Employment Medical Examination (PEME) conducted is in 22 accordance with prescribed and acceptable international standards, and the 23 requirements of the principal/employer. 24 25 The principal/employer shall shoulder the costs of the PEME of the seafarer under this 26 section, whatever the results of the said examination. 27 28",
  "is_repealed": false,
  "metadata": {
    "source_file": "[NOTICE TO PUBLIC] CLEAN DRAFT OF THE DMW SEABASED RULES.pdf",
    "jurisdiction": "PH",
    "corpus_category": "maritime_regulation",
    "parent_part": "PART II",
    "parent_rule": "RULE V",
    "timestamp": "2026-04-17T11:06:13.906978"
  }
}