{
  "jurisdiction": "PH",
  "section_id": "143",
  "title": "Freedom to Stipulate. Parties to the standard employment contract may",
  "content": "12 stipulate other terms and conditions, including benefits, which should be over and above 13 the minimum requirements. Said stipulations should not be contrary to law, morals, good 14 customs, public order, or public policy. 15 16",
  "is_repealed": false,
  "metadata": {
    "source_file": "[NOTICE TO PUBLIC] CLEAN DRAFT OF THE DMW SEABASED RULES.pdf",
    "jurisdiction": "PH",
    "corpus_category": "maritime_regulation",
    "parent_part": "PART IV",
    "parent_rule": "RULE I",
    "timestamp": "2026-04-17T11:06:14.855312"
  }
}