{
  "jurisdiction": "PH",
  "section_id": "84",
  "title": "Legal Assistance. The Department shall provide free legal service to",
  "content": "16 victims of illegal recruitment, trafficking in persons, and other related cases which are 17 administrative or criminal in nature in the form of legal advice, assistance in the 18 preparation of complaints and supporting documents, and institution of criminal actions. 19 20",
  "is_repealed": false,
  "metadata": {
    "source_file": "[NOTICE TO PUBLIC] CLEAN DRAFT OF THE DMW SEABASED RULES.pdf",
    "jurisdiction": "PH",
    "corpus_category": "maritime_regulation",
    "parent_part": "PART II",
    "parent_rule": "RULE XI",
    "timestamp": "2026-04-17T11:06:14.181060"
  }
}